LICENSE.txt
MANIFEST.in
README
requirements.txt
setup.py
ListeningSocketHandler/__init__.py
ListeningSocketHandler/handlers.py
ListeningSocketHandler.egg-info/PKG-INFO
ListeningSocketHandler.egg-info/SOURCES.txt
ListeningSocketHandler.egg-info/dependency_links.txt
ListeningSocketHandler.egg-info/top_level.txt
tests/__init__.py
tests/test_1.py