Metadata-Version: 1.0
Name: ListeningSocketHandler
Version: 0.1.0
Summary: The opposite of logging.handlers.SocketHandler
Home-page: https://github.com/bencord0/ListeningSocketHandler
Author: Ben Cordero
Author-email: bmc@linux.com
License: LICENSE.txt
Platform: UNKNOWN
